rietpy/__init__.py
rietpy/analysis.py
rietpy/constants.py
rietpy/engine.py
rietpy/parser.py
rietpy/plot.py
rietpy/preprocess.py
rietpy-0.1.9.dist-info/METADATA
rietpy-0.1.9.dist-info/WHEEL
rietpy-0.1.9.dist-info/RECORD
