Metadata-Version: 2.4
Name: rietpy
Version: 0.1.9
Summary: 
Author: tomooki
Author-email: tomooki0414@gmail.com
Requires-Python: >=3.13
Classifier: Programming Language :: Python :: 3
Classifier: Programming Language :: Python :: 3.13
Classifier: Programming Language :: Python :: 3.14
Requires-Dist: matplotlib (>=3.10.8,<4.0.0)
Requires-Dist: numpy (>=2.3.5,<3.0.0)
Requires-Dist: pandas (>=2.3.3,<3.0.0)
Requires-Dist: pathlib (>=1.0.1,<2.0.0)
